django_xss_detection
