Metadata-Version: 1.1
Name: django-xss-detection
Version: 0.4.15
Summary: # django xss detection
